datasette_llm_embed.py
datasette_llm_embed-0.2.dist-info/LICENSE
datasette_llm_embed-0.2.dist-info/METADATA
datasette_llm_embed-0.2.dist-info/WHEEL
datasette_llm_embed-0.2.dist-info/entry_points.txt
datasette_llm_embed-0.2.dist-info/top_level.txt
datasette_llm_embed-0.2.dist-info/RECORD
