Metadata-Version: 2.1
Name: datasette-llm-embed
Version: 0.2
Summary: llm_embed(model_id, text) SQL function for Datasette
Author: Simon Willison
License: Apache-2.0
Project-URL: Homepage, https://github.com/simonw/datasette-llm-embed
Project-URL: Changelog, https://github.com/simonw/datasette-llm-embed/releases
Project-URL: Issues, https://github.com/simonw/datasette-llm-embed/issues
Project-URL: CI, https://github.com/simonw/datasette-llm-embed/actions
Classifier: License :: OSI Approved :: Apache Software License
Classifier: Framework :: Datasette
License-File: LICENSE
Requires-Dist: datasette
Requires-Dist: llm
Provides-Extra: test
Requires-Dist: pytest ; extra == 'test'
Requires-Dist: pytest-asyncio ; extra == 'test'
